vip4model/Globals.py
vip4model/Model.py
vip4model/ModelCart.py
vip4model/Test.py
vip4model/_CoeffGrids.py
vip4model/_Legendre.py
vip4model/_ReadCoeffs.py
vip4model/_Schmidt.py
vip4model/_SphHarm.py
vip4model/__init__.py
vip4model/__data/coeffs.dat
vip4model-1.0.0.dist-info/LICENSE
vip4model-1.0.0.dist-info/METADATA
vip4model-1.0.0.dist-info/WHEEL
vip4model-1.0.0.dist-info/top_level.txt
vip4model-1.0.0.dist-info/RECORD
