Metadata-Version: 2.1
Name: vip4model
Version: 1.0.0
Summary: Python implementation of the VIP4 model
Home-page: https://github.com/mattkjames7/vip4model
Author: Matthew Knight James
Author-email: mattkjames7@gmail.com
License: UNKNOWN
Platform: UNKNOWN
Classifier: Programming Language :: Python :: 3
Classifier: License :: OSI Approved :: MIT License
Classifier: Operating System :: POSIX
Requires-Dist: numpy
Requires-Dist: PyFileIO
